bufflogin/__init__.py
bufflogin/buff.py
bufflogin/exceptions.py
bufflogin-0.0.6.dist-info/LICENSE
bufflogin-0.0.6.dist-info/METADATA
bufflogin-0.0.6.dist-info/WHEEL
bufflogin-0.0.6.dist-info/top_level.txt
bufflogin-0.0.6.dist-info/RECORD
