Metadata-Version: 2.1
Name: bufflogin
Version: 0.0.6
Summary: Authorization to buff.163.com through Steam
Home-page: https://github.com/sometastycake/bufflogin
Author: Mike M
Author-email: stopthisworldplease@outlook.com
License: MIT
Requires-Python: >=3.7
License-File: LICENSE
Requires-Dist: lxml (>=4.9.1)
Requires-Dist: pysteamauth (>=1.0.0)
Requires-Dist: cssselect (>=1.1.0)
